bytegapbuffer
