Metadata-Version: 1.0
Name: bytegapbuffer
Version: 0.9.2
Summary: A bytearray work-alike using a gap buffer for storage
Home-page: https://github.com/rjw57/bytegapbuffer
Author: Rich Wareham
Author-email: rich.bytegapbuffer@richwareham.com
License: UNKNOWN
Keywords: gap buffer,editor,collection
Platform: UNKNOWN
